chainwebpy/__init__.py
chainwebpy/url.py
chainwebpy/chainweb_p2p/__init__.py
chainwebpy/chainweb_p2p/block_hashes_endpoints.py
chainwebpy/chainweb_p2p/block_header_endpoints.py
chainwebpy/chainweb_p2p/block_payload_endpoints.py
chainwebpy/chainweb_p2p/config_endpoints.py
chainwebpy/chainweb_p2p/cut_endpoints.py
chainwebpy/chainweb_p2p/mempool_endpoints.py
chainwebpy/chainweb_p2p/peer_endpoints.py
chainwebpy/chainweb_service/__init__.py
chainwebpy/chainweb_service/mining_endpoints.py
chainwebpy/chainweb_service/miscellaneous_endpoints.py
chainwebpy/chainweb_service/pact_endpoints.py
tests/__init__.py
tests/test_bindings.py
chainweb.py-0.1.7.dist-info/LICENSE
chainweb.py-0.1.7.dist-info/METADATA
chainweb.py-0.1.7.dist-info/WHEEL
chainweb.py-0.1.7.dist-info/top_level.txt
chainweb.py-0.1.7.dist-info/RECORD
