Metadata-Version: 2.1
Name: chainweb.py
Version: 0.1.7
Summary: High level Python bindings for the Kadena Chainweb REST API.
Home-page: https://github.com/justmert/chainweb.py
Download-URL: https://github.com/justmert/chainweb.py/archive/refs/tags/0.1.7.tar.gz
Author: Mert Köklü
Author-email: mert@yuugen.art
License: MIT
Keywords: Kadena,Rest,Chainweb,API
Classifier: Development Status :: 3 - Alpha
Classifier: Intended Audience :: Developers
Classifier: Topic :: Software Development :: Libraries :: Python Modules
Classifier: License :: OSI Approved :: MIT License
Classifier: Programming Language :: Python :: 3.6
Classifier: Programming Language :: Python :: 3.7
Classifier: Programming Language :: Python :: 3.8
Classifier: Programming Language :: Python :: 3.9
License-File: LICENSE
Requires-Dist: requests
Requires-Dist: typing
